bbhx_cuda12x-1.2.3.dist-info/WHEEL
bbhx_cuda12x-1.2.3.dist-info/METADATA
bbhx_cuda12x-1.2.3.dist-info/RECORD
bbhx_cuda12x-1.2.3.dist-info/licenses/LICENSE
bbhx_backend_cuda12x/phenomhm.cpython-311-x86_64-linux-gnu.so
bbhx_backend_cuda12x/waveformbuild.cpython-311-x86_64-linux-gnu.so
bbhx_backend_cuda12x/git_version.py
bbhx_backend_cuda12x/response.cpython-311-x86_64-linux-gnu.so
bbhx_backend_cuda12x/interp.cpython-311-x86_64-linux-gnu.so
bbhx_backend_cuda12x/likelihood.cpython-311-x86_64-linux-gnu.so
lib64/python./site-packages/bbhx/response.cpython-311-x86_64-linux-gnu.so
