Metadata-Version: 2.2
Name: bbhx-cuda12x
Version: 1.2.3
Summary: GPU/CPU Binary Black Hole Waveforms for LISA.
Author: Michael Katz, Lorenzo Speri, Christian Chapman-Bird, Alvin J. K. Chua, Niels Warburton, Scott Hughes
Maintainer-Email: Michael Katz <mikekatz04@gmail.com>, Christian Chapman-Bird <c.chapmanbird@gmail.com>
Classifier: Environment :: GPU :: NVIDIA CUDA
Classifier: License :: OSI Approved :: MIT License
Classifier: Natural Language :: English
Classifier: Programming Language :: C++
Classifier: Programming Language :: Cython
Classifier: Programming Language :: Python :: 3 :: Only
Classifier: Programming Language :: Python :: 3.9
Classifier: Programming Language :: Python :: 3.10
Classifier: Programming Language :: Python :: 3.11
Classifier: Programming Language :: Python :: 3.12
Classifier: Programming Language :: Python :: 3.13
Project-URL: Documentation, https://bbhx.readthedocs.io/en/stable
Project-URL: Download, https://pypi.org/project/bbhx/#files
Requires-Python: >=3.9
Requires-Dist: exceptiongroup; python_version < "3.11"
Requires-Dist: h5py
Requires-Dist: jsonschema
Requires-Dist: lisaconstants
Requires-Dist: multispline
Requires-Dist: numba
Requires-Dist: numpy
Requires-Dist: nvidia-ml-py
Requires-Dist: platformdirs
Requires-Dist: pydantic
Requires-Dist: pyyaml
Requires-Dist: requests
Requires-Dist: rich
Requires-Dist: scipy
Requires-Dist: tqdm
Requires-Dist: wrapt
Requires-Dist: gpubackendtools
Requires-Dist: lisaanalysistools
Requires-Dist: cupy-cuda12x
Requires-Dist: bbhx==1.2.3
Provides-Extra: doc
Requires-Dist: ipykernel; extra == "doc"
Requires-Dist: ipython; extra == "doc"
Requires-Dist: ipywidgets; extra == "doc"
Requires-Dist: myst-parser; extra == "doc"
Requires-Dist: nbsphinx; extra == "doc"
Requires-Dist: pypandoc; extra == "doc"
Requires-Dist: sphinx; extra == "doc"
Requires-Dist: sphinx-rtd-theme; extra == "doc"
Requires-Dist: sphinx-tippy; extra == "doc"
Provides-Extra: sampling
Requires-Dist: eryn; extra == "sampling"
Requires-Dist: fastlisaresponse; extra == "sampling"
Requires-Dist: lisaanalysistools; extra == "sampling"
Requires-Dist: lisatools; extra == "sampling"
Provides-Extra: testing
Requires-Dist: matplotlib; extra == "testing"
